lineageot/__init__.py
lineageot/core.py
lineageot/evaluation.py
lineageot/inference.py
lineageot/simulation.py
lineageot-0.2.0.dist-info/LICENSE
lineageot-0.2.0.dist-info/METADATA
lineageot-0.2.0.dist-info/WHEEL
lineageot-0.2.0.dist-info/top_level.txt
lineageot-0.2.0.dist-info/RECORD
