Metadata-Version: 2.1
Name: lineageot
Version: 0.2.0
Summary: LineageOT
Home-page: https://github.com/aforr/LineageOT
Author: Aden Forrow
Author-email: aden.forrow@maths.ox.ac.uk
License: UNKNOWN
Platform: UNKNOWN
Classifier: Programming Language :: Python :: 3
Classifier: License :: OSI Approved :: MIT License
Classifier: Operating System :: OS Independent
Requires-Python: >=3.6
License-File: LICENSE
